latex_image_generator/__init__.py
latex_image_generator/config.py
latex_image_generator/execute_command.py
latex_image_generator/generate_image.py
latex_image_generator/main.py
latex_image_generator-0.1.0a3.dist-info/METADATA
latex_image_generator-0.1.0a3.dist-info/WHEEL
latex_image_generator-0.1.0a3.dist-info/entry_points.txt
latex_image_generator-0.1.0a3.dist-info/RECORD
